sheetshuttle/__init__.py
sheetshuttle/github_interaction.py
sheetshuttle/github_objects.py
sheetshuttle/main.py
sheetshuttle/sheet_collector.py
sheetshuttle/util.py
sheetshuttle-0.1.0.dist-info/entry_points.txt
sheetshuttle-0.1.0.dist-info/LICENSE
sheetshuttle-0.1.0.dist-info/WHEEL
sheetshuttle-0.1.0.dist-info/METADATA
sheetshuttle-0.1.0.dist-info/RECORD
